{
  "horizon": 5,
  "threshold": 0.02,
  "symbols": [
    "VCB",
    "BID",
    "CTG",
    "TCB",
    "MBB",
    "VPB",
    "ACB",
    "HDB",
    "STB",
    "TPB",
    "VIB",
    "SHB",
    "SSB",
    "LPB",
    "EIB",
    "VIC",
    "VHM",
    "VRE",
    "BCM",
    "VGI",
    "GAS",
    "PLX",
    "HPG",
    "GVR",
    "VNM",
    "MSN",
    "MWG",
    "SAB",
    "SSI",
    "FPT",
    "KDH",
    "DXG",
    "NVL",
    "PDR",
    "DIG",
    "BCG",
    "POW",
    "REE",
    "DGW",
    "NT2",
    "BSR",
    "PNJ",
    "FRT",
    "VHC",
    "DGC",
    "VJC",
    "HVN",
    "VND",
    "HNG",
    "VGC"
  ],
  "n_symbols": 50,
  "model_name": "trend_classifier",
  "version": "20260102_101243",
  "saved_at": "2026-01-02T10:12:43.897761",
  "model_type": "random_forest",
  "feature_names": [
    "return_1d",
    "return_5d",
    "return_10d",
    "return_20d",
    "volatility_5d",
    "volatility_20d",
    "sma_5",
    "sma_10",
    "sma_20",
    "sma_50",
    "price_vs_sma5",
    "price_vs_sma20",
    "price_vs_sma50",
    "sma5_vs_sma20",
    "sma20_vs_sma50",
    "rsi_14",
    "macd",
    "macd_signal",
    "macd_diff",
    "volume_change",
    "volume_ma_5",
    "volume_vs_ma",
    "hl_range",
    "momentum_5",
    "momentum_10",
    "momentum_20",
    "return_1d_lag1",
    "return_1d_lag2",
    "return_1d_lag3",
    "return_1d_lag5",
    "rsi_14_lag1",
    "rsi_14_lag2",
    "rsi_14_lag3",
    "rsi_14_lag5",
    "macd_diff_lag1",
    "macd_diff_lag2",
    "macd_diff_lag3",
    "macd_diff_lag5",
    "volume_change_lag1",
    "volume_change_lag2",
    "volume_change_lag3",
    "volume_change_lag5",
    "return_1d_mean_5",
    "return_1d_std_5",
    "return_1d_min_5",
    "return_1d_max_5",
    "return_1d_mean_10",
    "return_1d_std_10",
    "return_1d_min_10",
    "return_1d_max_10",
    "return_1d_mean_20",
    "return_1d_std_20",
    "return_1d_min_20",
    "return_1d_max_20",
    "volume_mean_5",
    "volume_std_5",
    "volume_min_5",
    "volume_max_5",
    "volume_mean_10",
    "volume_std_10",
    "volume_min_10",
    "volume_max_10",
    "volume_mean_20",
    "volume_std_20",
    "volume_min_20",
    "volume_max_20"
  ],
  "metrics": {
    "train_accuracy": 0.6021370420624153,
    "test_accuracy": 0.5131614654002714,
    "classification_report": {
      "DOWN": {
        "precision": 0.5962059620596206,
        "recall": 0.11982570806100218,
        "f1-score": 0.19954648526077098,
        "support": 1836.0
      },
      "NEUTRAL": {
        "precision": 0.5061900610287707,
        "recall": 0.8670848267622461,
        "f1-score": 0.6392161180226797,
        "support": 3348.0
      },
      "UP": {
        "precision": 0.5205371248025277,
        "recall": 0.30146386093321137,
        "f1-score": 0.38180764774044035,
        "support": 2186.0
      },
      "accuracy": 0.5131614654002714,
      "macro avg": {
        "precision": 0.5409777159636396,
        "recall": 0.42945813191881993,
        "f1-score": 0.40685675034129704,
        "support": 7370.0
      },
      "weighted avg": {
        "precision": 0.5328700984374645,
        "recall": 0.5131614654002714,
        "f1-score": 0.453337100141019,
        "support": 7370.0
      }
    },
    "train_samples": 29480,
    "test_samples": 7370,
    "n_features": 66
  }
}